cryptochart/__init__.py
cryptochart/__main__.py
cryptochart/chart.py
cryptochart/kraken.py
cryptochart/main.py
cryptochart/py.typed
python_cryptochart-0.0.2.dist-info/LICENSE.md
python_cryptochart-0.0.2.dist-info/METADATA
python_cryptochart-0.0.2.dist-info/WHEEL
python_cryptochart-0.0.2.dist-info/top_level.txt
python_cryptochart-0.0.2.dist-info/RECORD
