Metadata-Version: 2.1
Name: python-cryptochart
Version: 0.0.2
Summary: Terminal chart for crypto currencies
Home-page: https://github.com/FusionSolutions/python-cryptochart
Author: Andor `iFA` Rajci - Fusions Solutions KFT
Author-email: ifa@fusionsolutions.io
License: GPL-3
Keywords: crypto currency bitcoin chart ascii terminal
Platform: UNKNOWN
Classifier: Development Status :: 4 - Beta
Classifier: Topic :: Terminals
Classifier: Programming Language :: Python :: 3 :: Only
Classifier: Programming Language :: Python :: 3.7
Classifier: Programming Language :: Python :: 3.8
Classifier: Programming Language :: Python :: 3.9
Classifier: License :: OSI Approved :: GNU Lesser General Public License v3 or later (LGPLv3+)
Requires-Python: >=3.7.0
Requires-Dist: websocket-client
